{
    "key": "group_53d907e77fcb8",
    "title": "News Page Options",
    "fields": [
        {
            "key": "field_54060d9774daa",
            "label": "Callout Text",
            "name": "callout_text",
            "type": "textarea",
            "instructions": "Insert Callout Text Here",
            "required": 0,
            "conditional_logic": 0,
            "wrapper": {
                "width": "",
                "class": "",
                "id": ""
            },
            "default_value": "",
            "placeholder": "Insert Callout Text Here",
            "maxlength": "",
            "rows": "",
            "new_lines": "",
            "readonly": 0,
            "disabled": 0
        },
        {
            "key": "field_54060d9c74dab",
            "label": "Background Image",
            "name": "background_image",
            "type": "image",
            "instructions": "",
            "required": 0,
            "conditional_logic": 0,
            "wrapper": {
                "width": "",
                "class": "",
                "id": ""
            },
            "return_format": "array",
            "preview_size": "thumbnail",
            "library": "all",
            "min_width": 0,
            "min_height": 0,
            "min_size": 0,
            "max_width": 0,
            "max_height": 0,
            "max_size": 0,
            "mime_types": ""
        },
        {
            "key": "field_54105fa7daa09",
            "label": "Sidebar Note",
            "name": "sidebar_note",
            "type": "textarea",
            "instructions": "This text appears at the top of the sidebar.",
            "required": 0,
            "conditional_logic": 0,
            "wrapper": {
                "width": "",
                "class": "",
                "id": ""
            },
            "default_value": "",
            "placeholder": "",
            "maxlength": "",
            "rows": "",
            "new_lines": "wpautop",
            "readonly": 0,
            "disabled": 0
        },
        {
            "key": "field_5400d7127bb5e",
            "label": "Number of Links to Show",
            "name": "number_of_links_to_show",
            "type": "number",
            "instructions": "This decides how many links to show on the sidebar for each category. All other links will be displayed on an archive page.",
            "required": 0,
            "conditional_logic": 0,
            "wrapper": {
                "width": "",
                "class": "",
                "id": ""
            },
            "default_value": 5,
            "placeholder": "",
            "prepend": "",
            "append": "",
            "min": "",
            "max": "",
            "step": "",
            "readonly": 0,
            "disabled": 0
        },
        {
            "key": "field_53d907ecd8829",
            "label": "News Coverage",
            "name": "",
            "type": "tab",
            "instructions": "",
            "required": 0,
            "conditional_logic": 0,
            "wrapper": {
                "width": "",
                "class": "",
                "id": ""
            },
            "placement": "top",
            "endpoint": 0
        },
        {
            "key": "field_53d90854d882a",
            "label": "News Link",
            "name": "news_link",
            "type": "repeater",
            "instructions": "",
            "required": 0,
            "conditional_logic": 0,
            "wrapper": {
                "width": "",
                "class": "",
                "id": ""
            },
            "min": 0,
            "max": 0,
            "layout": "table",
            "button_label": "Add Row",
            "sub_fields": [
                {
                    "key": "field_53d9086bd882b",
                    "label": "Title",
                    "name": "title",
                    "type": "text",
                    "instructions": "",
                    "required": 0,
                    "conditional_logic": 0,
                    "wrapper": {
                        "width": "",
                        "class": "",
                        "id": ""
                    },
                    "default_value": "",
                    "placeholder": "",
                    "prepend": "",
                    "append": "",
                    "maxlength": "",
                    "readonly": 0,
                    "disabled": 0
                },
                {
                    "key": "field_53d90884d882c",
                    "label": "URL",
                    "name": "url",
                    "type": "text",
                    "instructions": "",
                    "required": 0,
                    "conditional_logic": 0,
                    "wrapper": {
                        "width": "",
                        "class": "",
                        "id": ""
                    },
                    "default_value": "",
                    "placeholder": "",
                    "prepend": "",
                    "append": "",
                    "maxlength": "",
                    "readonly": 0,
                    "disabled": 0
                },
                {
                    "key": "field_53d90893d882d",
                    "label": "Extra Info",
                    "name": "extra_info",
                    "type": "text",
                    "instructions": "",
                    "required": 0,
                    "conditional_logic": 0,
                    "wrapper": {
                        "width": "",
                        "class": "",
                        "id": ""
                    },
                    "default_value": "",
                    "placeholder": "Publication Name, Date",
                    "prepend": "",
                    "append": "",
                    "maxlength": "",
                    "readonly": 0,
                    "disabled": 0
                }
            ],
            "collapsed": ""
        },
        {
            "key": "field_53d908ded882f",
            "label": "Press Releases",
            "name": "",
            "type": "tab",
            "instructions": "",
            "required": 0,
            "conditional_logic": 0,
            "wrapper": {
                "width": "",
                "class": "",
                "id": ""
            },
            "placement": "top",
            "endpoint": 0
        },
        {
            "key": "field_53d9093ad8830",
            "label": "Press Release",
            "name": "press_release",
            "type": "repeater",
            "instructions": "If you need to upload a PDF, go to Media on the left menu and upload it there. Once uploaded, copy the File URL and paste it into the URL box here.",
            "required": 0,
            "conditional_logic": 0,
            "wrapper": {
                "width": "",
                "class": "",
                "id": ""
            },
            "min": 0,
            "max": 0,
            "layout": "table",
            "button_label": "Add Press Release",
            "sub_fields": [
                {
                    "key": "field_53d9093ad8831",
                    "label": "Title",
                    "name": "title",
                    "type": "text",
                    "instructions": "",
                    "required": 0,
                    "conditional_logic": 0,
                    "wrapper": {
                        "width": "",
                        "class": "",
                        "id": ""
                    },
                    "default_value": "",
                    "placeholder": "",
                    "prepend": "",
                    "append": "",
                    "maxlength": "",
                    "readonly": 0,
                    "disabled": 0
                },
                {
                    "key": "field_53d9093ad8832",
                    "label": "URL",
                    "name": "url",
                    "type": "text",
                    "instructions": "",
                    "required": 0,
                    "conditional_logic": 0,
                    "wrapper": {
                        "width": "",
                        "class": "",
                        "id": ""
                    },
                    "default_value": "",
                    "placeholder": "",
                    "prepend": "",
                    "append": "",
                    "maxlength": "",
                    "readonly": 0,
                    "disabled": 0
                },
                {
                    "key": "field_53d9131c5d552",
                    "label": "Extra Info",
                    "name": "extra_info",
                    "type": "text",
                    "instructions": "",
                    "required": 0,
                    "conditional_logic": 0,
                    "wrapper": {
                        "width": "",
                        "class": "",
                        "id": ""
                    },
                    "default_value": "",
                    "placeholder": "Date",
                    "prepend": "",
                    "append": "",
                    "maxlength": "",
                    "readonly": 0,
                    "disabled": 0
                }
            ],
            "collapsed": ""
        },
        {
            "key": "field_53d908dad882e",
            "label": "Newsletters",
            "name": "",
            "type": "tab",
            "instructions": "",
            "required": 0,
            "conditional_logic": 0,
            "wrapper": {
                "width": "",
                "class": "",
                "id": ""
            },
            "placement": "top",
            "endpoint": 0
        },
        {
            "key": "field_53d90959d8834",
            "label": "Newsletter",
            "name": "newsletter",
            "type": "repeater",
            "instructions": "",
            "required": 0,
            "conditional_logic": 0,
            "wrapper": {
                "width": "",
                "class": "",
                "id": ""
            },
            "min": 0,
            "max": 0,
            "layout": "table",
            "button_label": "Add Newsletter",
            "sub_fields": [
                {
                    "key": "field_53d90959d8835",
                    "label": "Title",
                    "name": "title",
                    "type": "text",
                    "instructions": "",
                    "required": 0,
                    "conditional_logic": 0,
                    "wrapper": {
                        "width": "",
                        "class": "",
                        "id": ""
                    },
                    "default_value": "",
                    "placeholder": "",
                    "prepend": "",
                    "append": "",
                    "maxlength": "",
                    "readonly": 0,
                    "disabled": 0
                },
                {
                    "key": "field_53d90959d8836",
                    "label": "URL",
                    "name": "url",
                    "type": "text",
                    "instructions": "",
                    "required": 0,
                    "conditional_logic": 0,
                    "wrapper": {
                        "width": "",
                        "class": "",
                        "id": ""
                    },
                    "default_value": "",
                    "placeholder": "",
                    "prepend": "",
                    "append": "",
                    "maxlength": "",
                    "readonly": 0,
                    "disabled": 0
                },
                {
                    "key": "field_53d913925d553",
                    "label": "Extra Info",
                    "name": "extra_info",
                    "type": "text",
                    "instructions": "",
                    "required": 0,
                    "conditional_logic": 0,
                    "wrapper": {
                        "width": "",
                        "class": "",
                        "id": ""
                    },
                    "default_value": "",
                    "placeholder": "Date",
                    "prepend": "",
                    "append": "",
                    "maxlength": "",
                    "readonly": 0,
                    "disabled": 0
                }
            ],
            "collapsed": ""
        },
        {
            "key": "field_59c145d747263",
            "label": "Banking on Buffalo Bayou",
            "name": "banking",
            "type": "repeater",
            "instructions": "",
            "required": 0,
            "conditional_logic": 0,
            "wrapper": {
                "width": "",
                "class": "",
                "id": ""
            },
            "collapsed": "",
            "min": 0,
            "max": 0,
            "layout": "table",
            "button_label": "Add Newsletter",
            "sub_fields": [
                {
                    "key": "field_59c145d747264",
                    "label": "Title",
                    "name": "title",
                    "type": "text",
                    "instructions": "",
                    "required": 0,
                    "conditional_logic": 0,
                    "wrapper": {
                        "width": "",
                        "class": "",
                        "id": ""
                    },
                    "default_value": "",
                    "placeholder": "",
                    "prepend": "",
                    "append": "",
                    "maxlength": ""
                },
                {
                    "key": "field_59c145d747265",
                    "label": "URL",
                    "name": "url",
                    "type": "text",
                    "instructions": "",
                    "required": 0,
                    "conditional_logic": 0,
                    "wrapper": {
                        "width": "",
                        "class": "",
                        "id": ""
                    },
                    "default_value": "",
                    "placeholder": "",
                    "prepend": "",
                    "append": "",
                    "maxlength": ""
                },
                {
                    "key": "field_59c145d747266",
                    "label": "Extra Info",
                    "name": "extra_info",
                    "type": "text",
                    "instructions": "",
                    "required": 0,
                    "conditional_logic": 0,
                    "wrapper": {
                        "width": "",
                        "class": "",
                        "id": ""
                    },
                    "default_value": "",
                    "placeholder": "Date",
                    "prepend": "",
                    "append": "",
                    "maxlength": ""
                }
            ]
        },
        {
            "key": "field_59c145b947262",
            "label": "Banking on Buffalo Bayou",
            "name": "",
            "type": "tab",
            "instructions": "",
            "required": 0,
            "conditional_logic": 0,
            "wrapper": {
                "width": "",
                "class": "",
                "id": ""
            },
            "placement": "top",
            "endpoint": 0
        }
    ],
    "location": [
        [
            {
                "param": "options_page",
                "operator": "==",
                "value": "acf-options-news-options"
            }
        ]
    ],
    "menu_order": 0,
    "position": "normal",
    "style": "default",
    "label_placement": "top",
    "instruction_placement": "label",
    "hide_on_screen": "",
    "active": 1,
    "description": "",
    "modified": 1505838767
}